sage_tools/__init__.py
sage_tools/apps.py
sage_tools/checks.py
sage_tools/context_processors/__init__.py
sage_tools/context_processors/maintenance.py
sage_tools/decorators/__init__.py
sage_tools/decorators/admin.py
sage_tools/encryptors/__init__.py
sage_tools/encryptors/base.py
sage_tools/encryptors/dummy.py
sage_tools/encryptors/fernet_encrypt.py
sage_tools/fields/__init__.py
sage_tools/fields/svg.py
sage_tools/forms/__init__.py
sage_tools/forms/timezone.py
sage_tools/handlers/__init__.py
sage_tools/handlers/file.py
sage_tools/handlers/session.py
sage_tools/helpers/__init__.py
sage_tools/helpers/typings.py
sage_tools/locale/ar/LC_MESSAGES/django.po
sage_tools/locale/en/LC_MESSAGES/django.po
sage_tools/locale/fa/LC_MESSAGES/django.mo
sage_tools/locale/fa/LC_MESSAGES/django.po
sage_tools/middlewares/__init__.py
sage_tools/middlewares/cookie.py
sage_tools/middlewares/csrf.py
sage_tools/middlewares/time_zone.py
sage_tools/mixins/__init__.py
sage_tools/mixins/admins/__init__.py
sage_tools/mixins/admins/limits.py
sage_tools/mixins/forms/__init__.py
sage_tools/mixins/forms/user.py
sage_tools/mixins/models/__init__.py
sage_tools/mixins/models/abstract.py
sage_tools/mixins/models/access.py
sage_tools/mixins/models/address.py
sage_tools/mixins/models/base.py
sage_tools/mixins/models/comment.py
sage_tools/mixins/models/rating.py
sage_tools/mixins/views/__init__.py
sage_tools/mixins/views/access.py
sage_tools/mixins/views/cache.py
sage_tools/mixins/views/http.py
sage_tools/mixins/views/locale.py
sage_tools/py.typed
sage_tools/repository/__init__.py
sage_tools/repository/generator/__init__.py
sage_tools/repository/generator/base.py
sage_tools/services/__init__.py
sage_tools/services/slug.py
sage_tools/tests/__init__.py
sage_tools/tests/conftest.py
sage_tools/tests/context_processors/__init__.py
sage_tools/tests/context_processors/test_maintenance.py
sage_tools/tests/decorators/__init__.py
sage_tools/tests/decorators/test_decorators.py
sage_tools/tests/encryptors/__init__.py
django_sage_tools-2.0.0.dist-info/LICENSE
django_sage_tools-2.0.0.dist-info/METADATA
django_sage_tools-2.0.0.dist-info/WHEEL
django_sage_tools-2.0.0.dist-info/RECORD
