Metadata-Version: 2.3
Name: django-sage-tools
Version: 2.0.0
Summary: Comprehensive Django utility package providing mixins, validators, decorators, and tools for enhanced Django development
License: MIT
Keywords: django,utilities,mixins,validators,tools,web-development,python,django-package
Author: Sepehr Akbarzadeh
Author-email: sepehr@sageteam.org
Maintainer: Sepehr Akbarzadeh
Maintainer-email: sepehr@sageteam.org
Requires-Python: >=3.8, !=2.7.*, !=3.0.*, !=3.1.*, !=3.2.*, !=3.3.*, !=3.4.*, !=3.5.*, !=3.6.*, !=3.7.*
Classifier: Development Status :: 4 - Beta
Classifier: Environment :: Web Environment
Classifier: Framework :: Django
Classifier: Framework :: Django :: 4.2
Classifier: Framework :: Django :: 5.0
Classifier: Framework :: Django :: 5.1
Classifier: Framework :: Django :: 5.2
Classifier: Intended Audience :: Developers
Classifier: License :: OSI Approved :: MIT License
Classifier: Operating System :: OS Independent
Classifier: Programming Language :: Python
Classifier: Programming Language :: Python :: 3
Classifier: Programming Language :: Python :: 3.8
Classifier: Programming Language :: Python :: 3.10
Classifier: Programming Language :: Python :: 3.11
Classifier: Programming Language :: Python :: 3.12
Classifier: Programming Language :: Python :: 3.13
Classifier: Programming Language :: Python :: 3.9
Classifier: Topic :: Internet :: WWW/HTTP
Classifier: Topic :: Internet :: WWW/HTTP :: Dynamic Content
Classifier: Topic :: Software Development :: Libraries :: Application Frameworks
Classifier: Topic :: Software Development :: Libraries :: Python Modules
Classifier: Typing :: Typed
Requires-Dist: cryptography (>=45.0.4,<46.0.0)
Requires-Dist: django (>=4.2,<5.0) ; python_version >= "3.8" and python_version < "3.10"
Requires-Dist: django (>=4.2,<5.3) ; python_version >= "3.10"
Requires-Dist: mimesis (>=11.1.0,<12.0.0)
Requires-Dist: pillow (>=10.4.0,<11.0.0)
Project-URL: Bug Tracker, https://github.com/sageteamorg/django-sage-tools/issues
Project-URL: Changelog, https://github.com/sageteamorg/django-sage-tools/blob/main/CHANGELOG.md
Project-URL: Documentation, https://django-sage-tools.readthedocs.io/
Project-URL: Discussions, https://github.com/sageteamorg/django-sage-tools/discussions
Project-URL: Homepage, https://github.com/sageteamorg/django-sage-tools
Project-URL: Repository, https://github.com/sageteamorg/django-sage-tools
